heartcovid.py
heartcovid-0.0.1.dist-info/METADATA
heartcovid-0.0.1.dist-info/WHEEL
heartcovid-0.0.1.dist-info/entry_points.txt
heartcovid-0.0.1.dist-info/top_level.txt
heartcovid-0.0.1.dist-info/RECORD
