Metadata-Version: 2.1
Name: heartcovid
Version: 0.0.1
Summary: Various numerical output and graphing software related to heart disease and Covid-19
Home-page: https://github.com/i-inose/heartcovid
Author: Izuru Inose
Author-email: i.inose0304@gmail.com
Project-URL: Bug Tracker, https://github.com/i-inose/heartcovid
Classifier: Programming Language :: Python :: 3
Classifier: License :: OSI Approved :: MIT License
Classifier: Operating System :: OS Independent
Requires-Python: >=3.7
